{"properties": [
  {
    "name": "jwt.private-key",
    "type": "java.lang.String",
    "description": "Path to private key file"
  },
  {
    "name": "jwt.public-key",
    "type": "java.lang.String",
    "description": "Path to public key file"
  },
  {
    "name": "upload.image-upload-directory",
    "type": "java.lang.String",
    "description": "A description for 'upload.image-upload-directory'"
  },
  {
    "name": "upload.max-image-upload-size",
    "type": "java.lang.String",
    "description": "A description for 'upload.max-image-upload-size'"
  }
]}